{"id": "mines_lithium", "fetched_at": "2026-03-26T12:27:29.092040+00:00", "feature_count": 10, "name": "Mines de lithium", "category": "ressources", "icon": "🔋", "ttl_hours": 720, "stale": false, "features": [{"type": "Feature", "geometry": {"type": "Point", "coordinates": [-68.5, -23.5]}, "properties": {"name": "Salar de Atacama", "country": "CL", "mineral": "Lithium", "operator": "SQM/Albemarle", "pct_global": 26}}, {"type": "Feature", "geometry": {"type": "Point", "coordinates": [-67.0, -23.9]}, "properties": {"name": "Salar de Olaroz", "country": "AR", "mineral": "Lithium", "operator": "Allkem"}}, {"type": "Feature", "geometry": {"type": "Point", "coordinates": [-67.5, -20.3]}, "properties": {"name": "Salar de Uyuni", "country": "BO", "mineral": "Lithium", "operator": "YLB"}}, {"type": "Feature", "geometry": {"type": "Point", "coordinates": [114.0, 36.0]}, "properties": {"name": "Jiangxi (Spodumene)", "country": "CN", "mineral": "Lithium", "operator": "Ganfeng"}}, {"type": "Feature", "geometry": {"type": "Point", "coordinates": [101.0, 37.0]}, "properties": {"name": "Qinghai Salt Lake", "country": "CN", "mineral": "Lithium", "operator": "Qinghai Salt Lake"}}, {"type": "Feature", "geometry": {"type": "Point", "coordinates": [121.6, -33.8]}, "properties": {"name": "Greenbushes", "country": "AU", "mineral": "Lithium", "operator": "Tianqi/IGO", "pct_global": 20}}, {"type": "Feature", "geometry": {"type": "Point", "coordinates": [121.2, -31.1]}, "properties": {"name": "Mt Marion", "country": "AU", "mineral": "Lithium", "operator": "Mineral Resources"}}, {"type": "Feature", "geometry": {"type": "Point", "coordinates": [-117.4, 35.8]}, "properties": {"name": "Silver Peak", "country": "US", "mineral": "Lithium", "operator": "Albemarle"}}, {"type": "Feature", "geometry": {"type": "Point", "coordinates": [-117.2, 40.9]}, "properties": {"name": "Thacker Pass", "country": "US", "mineral": "Lithium", "operator": "Lithium Americas"}}, {"type": "Feature", "geometry": {"type": "Point", "coordinates": [25.5, -29.2]}, "properties": {"name": "Jadar (projet)", "country": "RS", "mineral": "Lithium", "operator": "Rio Tinto", "status": "projet"}}]}